[
    {
        "name": "first_tab",
        "sections": [
            {
                "label": "Details",
                "name": "details_section",
                "opened": true,
                "columns": [
                    {
                        "name": "column_z9XL",
                        "fields": [
                            "organization",
                            "annual_revenue",
                            "next_step"
                        ]
                    },
                    {
                        "name": "column_gM4w",
                        "fields": [
                            "website",
                            "closed_date",
                            "deal_owner"
                        ]
                    },
                    {
                        "name": "column_gWmE",
                        "fields": [
                            "territory",
                            "probability"
                        ]
                    }
                ]
            },
            {
                "label": "Products",
                "name": "section_jHhQ",
                "opened": true,
                "columns": [
                    {
                        "name": "column_xiNF",
                        "fields": [
                            "products"
                        ]
                    }
                ],
                "editingLabel": false,
                "hideLabel": true
            },
            {
                "label": "New Section",
                "name": "section_WNOQ",
                "opened": true,
                "columns": [
                    {
                        "name": "column_ziBW",
                        "fields": [
                            "total"
                        ]
                    },
                    {
                        "label": "",
                        "name": "column_wuwA",
                        "fields": [
                            "net_total"
                        ]
                    }
                ],
                "hideBorder": true,
                "hideLabel": true
            }
        ]
    }
]